trabalho_gces_denys/__init__.py
trabalho_gces_denys-0.1.0.dist-info/LICENSE
trabalho_gces_denys-0.1.0.dist-info/WHEEL
trabalho_gces_denys-0.1.0.dist-info/METADATA
trabalho_gces_denys-0.1.0.dist-info/RECORD
