Metadata-Version: 2.1
Name: trabalho-gces-denys
Version: 0.1.0
Summary: 
Author: DenysRogeres
Author-email: dennysrogeres@gmail.com
Requires-Python: >=3.10,<4.0
Classifier: Programming Language :: Python :: 3
Classifier: Programming Language :: Python :: 3.10
Classifier: Programming Language :: Python :: 3.11
